xdbc_client/__init__.py
xdbc_client/client.py
xdbc_client/exceptions.py
xdbc_client/models.py
xdbc_client-0.1.0.dist-info/licenses/LICENSE
xdbc_client-0.1.0.dist-info/METADATA
xdbc_client-0.1.0.dist-info/WHEEL
xdbc_client-0.1.0.dist-info/top_level.txt
xdbc_client-0.1.0.dist-info/RECORD
